mergepdf/__init__.py
mergepdf/__main__.py
mergepdf/py.typed
mergepdf-0.4.1.dist-info/METADATA
mergepdf-0.4.1.dist-info/WHEEL
mergepdf-0.4.1.dist-info/entry_points.txt
mergepdf-0.4.1.dist-info/licenses/LICENSE
mergepdf-0.4.1.dist-info/RECORD
