Metadata-Version: 2.3
Name: mergepdf
Version: 0.4.1
Summary: `mergepdf` is a package for merge PDF files.
Project-URL: homepage, https://github.com/SaitoTsutomu/mergepdf
Author-email: Saito Tsutomu <tsutomu7@hotmail.co.jp>
License: Apache-2.0
License-File: LICENSE
Classifier: Development Status :: 1 - Planning
Classifier: License :: OSI Approved :: Apache Software License
Classifier: Programming Language :: Python
Classifier: Topic :: Scientific/Engineering
Classifier: Topic :: Software Development
Requires-Python: >=3.12
Requires-Dist: pypdf>=5.0.0
